.coveragerc
.testr.conf
AUTHORS
ChangeLog
README.rst
config.py
config.yml
install.txt
requirement-conda.txt
requirements.txt
setup.cfg
setup.py
template_test.pytemplate
test-requirements.txt
tox.ini
commutils/__init__.py
commutils/cli.py
commutils/cy.py
commutils/essential.py
commutils/gy.py
commutils/ly.py
commutils/monkey_patch.py
commutils/reflection.py
commutils/shell_task.py
commutils/smartlog.py
commutils/timecount.py
commutils/unit.py
commutils/version.py
commutils/yml_config.py
commutils.egg-info/PKG-INFO
commutils.egg-info/SOURCES.txt
commutils.egg-info/dependency_links.txt
commutils.egg-info/entry_points.txt
commutils.egg-info/not-zip-safe
commutils.egg-info/pbr.json
commutils.egg-info/requires.txt
commutils.egg-info/top_level.txt
commutils/project_gen/__init__.py
commutils/project_gen/target/commutils/.coveragerc
commutils/project_gen/target/commutils/.gitignore
commutils/project_gen/target/commutils/.testr.conf
commutils/project_gen/target/commutils/README.md
commutils/project_gen/target/commutils/requirement-conda.txt
commutils/project_gen/target/commutils/requirements.txt
commutils/project_gen/target/commutils/setup.cfg
commutils/project_gen/target/commutils/setup.py
commutils/project_gen/target/commutils/test-requirements.txt
commutils/project_gen/target/commutils/tox.ini
commutils/project_gen/target/commutils/docs/Makefile
commutils/project_gen/target/commutils/docs/make.bat
commutils/project_gen/target/commutils/docs/source/conf.py
commutils/project_gen/target/commutils/docs/source/index.rst
commutils/project_gen/template/project/.coveragerc
commutils/project_gen/template/project/.gitignore
commutils/project_gen/template/project/.testr.conf
commutils/project_gen/template/project/README.rst
commutils/project_gen/template/project/config.py
commutils/project_gen/template/project/config.yml
commutils/project_gen/template/project/requirement-conda.txt
commutils/project_gen/template/project/requirements.txt
commutils/project_gen/template/project/setup.cfg
commutils/project_gen/template/project/setup.py
commutils/project_gen/template/project/template_test.pytemplate
commutils/project_gen/template/project/test-requirements.txt
commutils/project_gen/template/project/tox.ini
